russell/__init__.py
russell/config.py
russell/constants.py
russell/date_utils.py
russell/exceptions.py
russell/log.py
russell/main.py
russell/cli/__init__.py
russell/cli/auth.py
russell/cli/data.py
russell/cli/experiment.py
russell/cli/run.py
russell/cli/utils.py
russell/client/__init__.py
russell/client/auth.py
russell/client/base.py
russell/client/common.py
russell/client/data.py
russell/client/experiment.py
russell/client/files.py
russell/client/module.py
russell/client/task_instance.py
russell/client/usage.py
russell/client/version.py
russell/development/__init__.py
russell/development/dev.py
russell/development/local.py
russell/manager/__init__.py
russell/manager/auth_config.py
russell/manager/data_config.py
russell/manager/experiment_config.py
russell/manager/russell_ignore.py
russell/model/__init__.py
russell/model/access_token.py
russell/model/base.py
russell/model/credentials.py
russell/model/data.py
russell/model/experiment.py
russell/model/experiment_config.py
russell/model/module.py
russell/model/task_instance.py
russell/model/user.py
russell/model/version.py
russell_cli-0.1.8.dist-info/DESCRIPTION.rst
russell_cli-0.1.8.dist-info/entry_points.txt
russell_cli-0.1.8.dist-info/METADATA
russell_cli-0.1.8.dist-info/metadata.json
russell_cli-0.1.8.dist-info/RECORD
russell_cli-0.1.8.dist-info/top_level.txt
russell_cli-0.1.8.dist-info/WHEEL
