Metadata-Version: 2.0
Name: russell-cli
Version: 0.1.8
Summary: Command line tool for russell
Home-page: https://github.com/RussellCloud/russell-cli
Author: Russell
Author-email: support@russellcloud.cn
License: UNKNOWN
Keywords: russell
Platform: UNKNOWN
Requires-Dist: click (>=6.7)
Requires-Dist: requests (>=2.12.4)
Requires-Dist: marshmallow (>=2.11.1)
Requires-Dist: pytz (>=2016.10)
Requires-Dist: shortuuid (>=0.4.3)
Requires-Dist: tabulate (>=0.7.7)
